ghidriff/__init__.py
ghidriff/__main__.py
ghidriff/bsim.py
ghidriff/correlators.py
ghidriff/decomp_correlate.py
ghidriff/ghidra_diff_engine.py
ghidriff/implied_matches.py
ghidriff/markdown.py
ghidriff/parser.py
ghidriff/simple_diff.py
ghidriff/structural_graph_diff.py
ghidriff/utils.py
ghidriff/version_tracking_diff.py
ghidriff-1.0.0.dist-info/LICENSE
ghidriff-1.0.0.dist-info/METADATA
ghidriff-1.0.0.dist-info/WHEEL
ghidriff-1.0.0.dist-info/entry_points.txt
ghidriff-1.0.0.dist-info/top_level.txt
ghidriff-1.0.0.dist-info/RECORD
