Metadata-Version: 2.1
Name: ghidriff
Version: 1.0.0
Summary: Ghidra Binary Diffing Engine
Home-page: https://github.com/clearbluejar/ghidriff
Author: clearbluejar
Author-email: clearbluejar@clearbluejar.com
License: GPL-3.0 license
Keywords: patchdiff,binaries,bindiff,ghidra,ghidriff
Platform: any
Classifier: Development Status :: 3 - Alpha
Classifier: Intended Audience :: Developers
Classifier: License :: OSI Approved :: GNU General Public License v3 (GPLv3)
Classifier: Programming Language :: Python :: 3
Classifier: Programming Language :: Python :: 3.9
Classifier: Programming Language :: Python :: 3.10
Classifier: Programming Language :: Python :: 3.11
Classifier: Programming Language :: Python :: 3.12
Requires-Python: >=3.9
License-File: LICENSE
Requires-Dist: pyghidra >=2.0.0
Requires-Dist: mdutils ==1.6.0
Provides-Extra: testing
Requires-Dist: pytest ; extra == 'testing'
Requires-Dist: requests ; extra == 'testing'
Requires-Dist: pytest-datadir ; extra == 'testing'
Requires-Dist: pytest-forked ; extra == 'testing'
Requires-Dist: pytest-xdist ; extra == 'testing'
